{"eur":{"code":"EUR","alphaCode":"EUR","numericCode":"978","name":"Euro","rate":0.9182864207685,"date":"Sat, 20 Jan 2024 11:55:01 GMT","inverseRate":1.0889848498066},"gbp":{"code":"GBP","alphaCode":"GBP","numericCode":"826","name":"U.K. Pound Sterling","rate":0.78802140455837,"date":"Sat, 20 Jan 2024 11:55:01 GMT","inverseRate":1.2690010629349},"jpy":{"code":"JPY","alphaCode":"JPY","numericCode":"392","name":"Japanese Yen","rate":148.02438180527,"date":"Sat, 20 Jan 2024 11:55:01 GMT","inverseRate":0.0067556438189725},"aud":{"code":"AUD","alphaCode":"AUD","numericCode":"036","name":"Australian Dollar","rate":1.5160980594137,"date":"Sat, 20 Jan 2024 11:55:01 GMT","inverseRate":0.65958794273948},"chf":{"code":"CHF","alphaCode":"CHF","numericCode":"756","name":"Swiss Franc","rate":0.86821262710832,"date":"Sat, 20 Jan 2024 11:55:01 GMT","inverseRate":1.1517915874256},"cad":{"code":"CAD","alphaCode":"CAD","numericCode":"124","name":"Canadian Dollar","rate":1.3464132318622,"date":"Sat, 20 Jan 2024 11:55:01 GMT","inverseRate":0.74271403187038},"dkk":{"code":"DKK","alphaCode":"DKK","numericCode":"208","name":"Danish Krone","rate":6.8507522065632,"date":"Sat, 20 Jan 2024 11:55:01 GMT","inverseRate":0.14596937239125},"lkr":{"code":"LKR","alphaCode":"LKR","numericCode":"144","name":"Sri Lanka Rupee","rate":323.92850990526,"date":"Sat, 20 Jan 2024 11:55:01 GMT","inverseRate":0.0030871009170896},"tnd":{"code":"TND","alphaCode":"TND","numericCode":"788","name":"Tunisian Dinar","rate":3.0694784549994,"date":"Sat, 20 Jan 2024 11:55:01 GMT","inverseRate":0.32578824535199},"vnd":{"code":"VND","alphaCode":"VND","numericCode":"704","name":"Vietnamese Dong","rate":24497.854057181,"date":"Sat, 20 Jan 2024 11:55:01 GMT","inverseRate":4.0819901925527e-5},"tmt":{"code":"TMT","alphaCode":"TMT","numericCode":"934","name":"New Turkmenistan Manat","rate":3.45623842987,"date":"Sat, 20 Jan 2024 11:55:01 GMT","inverseRate":0.28933189080871},"pkr":{"code":"PKR","alphaCode":"PKR","numericCode":"586","name":"Pakistani Rupee","rate":280.15529134873,"date":"Sat, 20 Jan 2024 11:55:01 GMT","inverseRate":0.0035694489123721},"bgn":{"code":"BGN","alphaCode":"BGN","numericCode":"975","name":"Bulgarian Lev","rate":1.796611838126,"date":"Sat, 20 Jan 2024 11:55:01 GMT","inverseRate":0.55660325662948},"rub":{"code":"RUB","alphaCode":"RUB","numericCode":"643","name":"Russian Rouble","rate":88.186745295883,"date":"Sat, 20 Jan 2024 11:55:01 GMT","inverseRate":0.011339572592738},"gel":{"code":"GEL","alphaCode":"GEL","numericCode":"981","name":"Georgian lari","rate":2.6538899457578,"date":"Sat, 20 Jan 2024 11:55:01 GMT","inverseRate":0.37680537642433},"sar":{"code":"SAR","alphaCode":"SAR","numericCode":"682","name":"Saudi Riyal","rate":3.7474194074122,"date":"Sat, 20 Jan 2024 11:55:01 GMT","inverseRate":0.26685030184293},"pln":{"code":"PLN","alphaCode":"PLN","numericCode":"985","name":"Polish Zloty","rate":4.0091939508027,"date":"Sat, 20 Jan 2024 11:55:01 GMT","inverseRate":0.24942669580747},"kzt":{"code":"KZT","alphaCode":"KZT","numericCode":"398","name":"Kazakhstani Tenge","rate":449.76748645668,"date":"Sat, 20 Jan 2024 11:55:01 GMT","inverseRate":0.0022233710308367},"cop":{"code":"COP","alphaCode":"COP","numericCode":"170","name":"Colombian Peso","rate":3919.9999999999,"date":"Sat, 20 Jan 2024 11:55:01 GMT","inverseRate":0.00025510204081633},"bhd":{"code":"BHD","alphaCode":"BHD","numericCode":"048","name":"Bahrain Dinar","rate":0.376081,"date":"Sat, 20 Jan 2024 11:55:01 GMT","inverseRate":2.65900165124},"egp":{"code":"EGP","alphaCode":"EGP","numericCode":"818","name":"Egyptian Pound","rate":30.897112154998,"date":"Sat, 20 Jan 2024 11:55:01 GMT","inverseRate":0.032365484352823},"krw":{"code":"KRW","alphaCode":"KRW","numericCode":"410","name":"South Korean Won","rate":1335.1620916602,"date":"Sat, 20 Jan 2024 11:55:01 GMT","inverseRate":0.00074897273240926},"dzd":{"code":"DZD","alphaCode":"DZD","numericCode":"012","name":"Algerian Dinar","rate":133.38112595678,"date":"Sat, 20 Jan 2024 11:55:01 GMT","inverseRate":0.0074973126282052},"pab":{"code":"PAB","alphaCode":"PAB","numericCode":"590","name":"Panamanian Balboa","rate":1,"date":"Sat, 20 Jan 2024 11:55:01 GMT","inverseRate":1},"hkd":{"code":"HKD","alphaCode":"HKD","numericCode":"344","name":"Hong Kong Dollar","rate":7.8191324467236,"date":"Sat, 20 Jan 2024 11:55:01 GMT","inverseRate":0.12789142616698},"mad":{"code":"MAD","alphaCode":"MAD","numericCode":"504","name":"Moroccan Dirham","rate":9.7725272002444,"date":"Sat, 20 Jan 2024 11:55:01 GMT","inverseRate":0.10232767630209},"zar":{"code":"ZAR","alphaCode":"ZAR","numericCode":"710","name":"South African Rand","rate":19.012022536259,"date":"Sat, 20 Jan 2024 11:55:01 GMT","inverseRate":0.052598296582746},"iqd":{"code":"IQD","alphaCode":"IQD","numericCode":"368","name":"Iraqi dinar","rate":1293.6261160329,"date":"Sat, 20 Jan 2024 11:55:01 GMT","inverseRate":0.00077302088107702},"bob":{"code":"BOB","alphaCode":"BOB","numericCode":"068","name":"Bolivian Boliviano","rate":6.8599999999998,"date":"Sat, 20 Jan 2024 11:55:01 GMT","inverseRate":0.14577259475219},"kwd":{"code":"KWD","alphaCode":"KWD","numericCode":"414","name":"Kuwaiti Dinar","rate":0.30738480047994,"date":"Sat, 20 Jan 2024 11:55:01 GMT","inverseRate":3.2532512942691},"thb":{"code":"THB","alphaCode":"THB","numericCode":"764","name":"Thai Baht","rate":35.399863838618,"date":"Sat, 20 Jan 2024 11:55:01 GMT","inverseRate":0.028248696225467},"twd":{"code":"TWD","alphaCode":"TWD","numericCode":"901","name":"New Taiwan Dollar ","rate":31.357919986728,"date":"Sat, 20 Jan 2024 11:55:01 GMT","inverseRate":0.031889870259993},"uzs":{"code":"UZS","alphaCode":"UZS","numericCode":"860","name":"Uzbekistan Sum","rate":12233.675631622,"date":"Sat, 20 Jan 2024 11:55:01 GMT","inverseRate":8.1741582016051e-5},"omr":{"code":"OMR","alphaCode":"OMR","numericCode":"512","name":"Omani Rial","rate":0.38474979769178,"date":"Sat, 20 Jan 2024 11:55:01 GMT","inverseRate":2.599091685036},"ils":{"code":"ILS","alphaCode":"ILS","numericCode":"376","name":"Israeli New Sheqel","rate":3.7347257890435,"date":"Sat, 20 Jan 2024 11:55:01 GMT","inverseRate":0.26775727496077},"pen":{"code":"PEN","alphaCode":"PEN","numericCode":"604","name":"Peruvian Nuevo Sol","rate":3.740575739097,"date":"Sat, 20 Jan 2024 11:55:01 GMT","inverseRate":0.26733852480191},"tjs":{"code":"TJS","alphaCode":"TJS","numericCode":"972","name":"Tajikistan Ruble","rate":10.817757278755,"date":"Sat, 20 Jan 2024 11:55:01 GMT","inverseRate":0.092440602449447},"sek":{"code":"SEK","alphaCode":"SEK","numericCode":"752","name":"Swedish Krona","rate":10.463771615626,"date":"Sat, 20 Jan 2024 11:55:01 GMT","inverseRate":0.095567835072648},"sgd":{"code":"SGD","alphaCode":"SGD","numericCode":"702","name":"Singapore Dollar","rate":1.3407969307247,"date":"Sat, 20 Jan 2024 11:55:01 GMT","inverseRate":0.74582509631753},"huf":{"code":"HUF","alphaCode":"HUF","numericCode":"348","name":"Hungarian Forint","rate":350.66455304467,"date":"Sat, 20 Jan 2024 11:55:01 GMT","inverseRate":0.0028517282152343},"uah":{"code":"UAH","alphaCode":"UAH","numericCode":"980","name":"Ukrainian Hryvnia","rate":37.519431044669,"date":"Sat, 20 Jan 2024 11:55:01 GMT","inverseRate":0.026652856190955},"clp":{"code":"CLP","alphaCode":"CLP","numericCode":"152","name":"Chilean Peso","rate":914.38372553824,"date":"Sat, 20 Jan 2024 11:55:01 GMT","inverseRate":0.0010936327627784},"dop":{"code":"DOP","alphaCode":"DOP","numericCode":"214","name":"Dominican Peso","rate":58.239200644817,"date":"Sat, 20 Jan 2024 11:55:01 GMT","inverseRate":0.017170565339636},"cny":{"code":"CNY","alphaCode":"CNY","numericCode":"156","name":"Chinese Yuan","rate":7.192197082186,"date":"Sat, 20 Jan 2024 11:55:01 GMT","inverseRate":0.13903957143734},"isk":{"code":"ISK","alphaCode":"ISK","numericCode":"352","name":"Icelandic Krona","rate":136.74906507794,"date":"Sat, 20 Jan 2024 11:55:01 GMT","inverseRate":0.0073126642542679},"azn":{"code":"AZN","alphaCode":"AZN","numericCode":"944","name":"Azerbaijan Manat","rate":1.6989985331136,"date":"Sat, 20 Jan 2024 11:55:01 GMT","inverseRate":0.58858202671158},"htg":{"code":"HTG","alphaCode":"HTG","numericCode":"332","name":"Haitian gourde","rate":131.51840490797,"date":"Sat, 20 Jan 2024 11:55:01 GMT","inverseRate":0.0076034985422744},"ang":{"code":"ANG","alphaCode":"ANG","numericCode":"532","name":"Neth. Antillean Guilder","rate":1.7900009995193,"date":"Sat, 20 Jan 2024 11:55:01 GMT","inverseRate":0.55865890592717},"lbp":{"code":"LBP","alphaCode":"LBP","numericCode":"422","name":"Lebanese Pound","rate":14954.133296486,"date":"Sat, 20 Jan 2024 11:55:01 GMT","inverseRate":6.6871143928815e-5},"myr":{"code":"MYR","alphaCode":"MYR","numericCode":"458","name":"Malaysian Ringgit","rate":4.7102987428895,"date":"Sat, 20 Jan 2024 11:55:01 GMT","inverseRate":0.21230075937531},"irr":{"code":"IRR","alphaCode":"IRR","numericCode":"364","name":"Iranian rial","rate":41474.784761442,"date":"Sat, 20 Jan 2024 11:55:01 GMT","inverseRate":2.4111035313429e-5},"uyu":{"code":"UYU","alphaCode":"UYU","numericCode":"858","name":"Uruguayan Peso","rate":39.137380191693,"date":"Sat, 20 Jan 2024 11:55:01 GMT","inverseRate":0.025551020408163},"jod":{"code":"JOD","alphaCode":"JOD","numericCode":"400","name":"Jordanian Dinar","rate":0.70916400954108,"date":"Sat, 20 Jan 2024 11:55:01 GMT","inverseRate":1.4101110413755},"php":{"code":"PHP","alphaCode":"PHP","numericCode":"608","name":"Philippine Peso","rate":55.951303312582,"date":"Sat, 20 Jan 2024 11:55:01 GMT","inverseRate":0.017872684652461},"xof":{"code":"XOF","alphaCode":"XOF","numericCode":"952","name":"West African CFA Franc","rate":602.94711268463,"date":"Sat, 20 Jan 2024 11:55:01 GMT","inverseRate":0.0016585202565238},"lyd":{"code":"LYD","alphaCode":"LYD","numericCode":"434","name":"Libyan Dinar","rate":4.7059089085072,"date":"Sat, 20 Jan 2024 11:55:01 GMT","inverseRate":0.21249880085699},"nzd":{"code":"NZD","alphaCode":"NZD","numericCode":"554","name":"New Zealand Dollar","rate":1.6352210609589,"date":"Sat, 20 Jan 2024 11:55:01 GMT","inverseRate":0.61153811180343},"try":{"code":"TRY","alphaCode":"TRY","numericCode":"949","name":"Turkish Lira","rate":30.160882789668,"date":"Sat, 20 Jan 2024 11:55:01 GMT","inverseRate":0.033155528204319},"ngn":{"code":"NGN","alphaCode":"NGN","numericCode":"566","name":"Nigerian Naira","rate":890.51270000004,"date":"Sat, 20 Jan 2024 11:55:01 GMT","inverseRate":0.0011229486115133},"rsd":{"code":"RSD","alphaCode":"RSD","numericCode":"941","name":"Serbian Dinar","rate":106.1766538166,"date":"Sat, 20 Jan 2024 11:55:01 GMT","inverseRate":0.0094182662954072},"nok":{"code":"NOK","alphaCode":"NOK","numericCode":"578","name":"Norwegian Krone","rate":10.474334674793,"date":"Sat, 20 Jan 2024 11:55:01 GMT","inverseRate":0.095471457715262},"qar":{"code":"QAR","alphaCode":"QAR","numericCode":"634","name":"Qatari Rial","rate":3.6459975375428,"date":"Sat, 20 Jan 2024 11:55:01 GMT","inverseRate":0.27427336132376},"czk":{"code":"CZK","alphaCode":"CZK","numericCode":"203","name":"Czech Koruna","rate":22.788034757744,"date":"Sat, 20 Jan 2024 11:55:01 GMT","inverseRate":0.043882678371823},"byn":{"code":"BYN","alphaCode":"BYN","numericCode":"933","name":"Belarussian Ruble","rate":3.272568306011,"date":"Sat, 20 Jan 2024 11:55:01 GMT","inverseRate":0.3055703980764},"ars":{"code":"ARS","alphaCode":"ARS","numericCode":"032","name":"Argentine Peso","rate":819.5937873357,"date":"Sat, 20 Jan 2024 11:55:01 GMT","inverseRate":0.0012201166180758},"ves":{"code":"VES","alphaCode":"VES","numericCode":"928","name":"Venezuelan Bolivar","rate":36.027649165049,"date":"Sat, 20 Jan 2024 11:55:01 GMT","inverseRate":0.027756459918293},"bdt":{"code":"BDT","alphaCode":"BDT","numericCode":"050","name":"Bangladeshi taka","rate":109.3587785925,"date":"Sat, 20 Jan 2024 11:55:01 GMT","inverseRate":0.0091442133212393},"ron":{"code":"RON","alphaCode":"RON","numericCode":"946","name":"Romanian New Leu","rate":4.5723664302157,"date":"Sat, 20 Jan 2024 11:55:01 GMT","inverseRate":0.21870513119676},"mdl":{"code":"MDL","alphaCode":"MDL","numericCode":"498","name":"Moldova Lei","rate":17.747490111593,"date":"Sat, 20 Jan 2024 11:55:01 GMT","inverseRate":0.056345995614714},"crc":{"code":"CRC","alphaCode":"CRC","numericCode":"188","name":"Costa Rican Col\u00f3n","rate":516.31628856282,"date":"Sat, 20 Jan 2024 11:55:01 GMT","inverseRate":0.0019367973123287},"aed":{"code":"AED","alphaCode":"AED","numericCode":"784","name":"U.A.E Dirham","rate":3.6613713187864,"date":"Sat, 20 Jan 2024 11:55:01 GMT","inverseRate":0.27312171122034},"idr":{"code":"IDR","alphaCode":"IDR","numericCode":"360","name":"Indonesian Rupiah","rate":15627.675618679,"date":"Sat, 20 Jan 2024 11:55:01 GMT","inverseRate":6.3989042542241e-5},"mxn":{"code":"MXN","alphaCode":"MXN","numericCode":"484","name":"Mexican Peso","rate":17.124700663254,"date":"Sat, 20 Jan 2024 11:55:01 GMT","inverseRate":0.058395181303565},"amd":{"code":"AMD","alphaCode":"AMD","numericCode":"051","name":"Armenia Dram","rate":399.72731436605,"date":"Sat, 20 Jan 2024 11:55:01 GMT","inverseRate":0.00250170544784},"pyg":{"code":"PYG","alphaCode":"PYG","numericCode":"600","name":"Paraguayan Guaran\u00ed","rate":7297.8723404251,"date":"Sat, 20 Jan 2024 11:55:01 GMT","inverseRate":0.00013702623906706},"brl":{"code":"BRL","alphaCode":"BRL","numericCode":"986","name":"Brazilian Real","rate":4.9142220774696,"date":"Sat, 20 Jan 2024 11:55:01 GMT","inverseRate":0.20349100716973},"inr":{"code":"INR","alphaCode":"INR","numericCode":"356","name":"Indian Rupee","rate":83.104631335612,"date":"Sat, 20 Jan 2024 11:55:01 GMT","inverseRate":0.012033023718757},"npr":{"code":"NPR","alphaCode":"NPR","numericCode":"524","name":"Nepalese Rupee","rate":133.26754075124,"date":"Sat, 20 Jan 2024 11:55:01 GMT","inverseRate":0.0075037026597994},"xaf":{"code":"XAF","alphaCode":"XAF","numericCode":"950","name":"Central African CFA Franc","rate":602.94711268463,"date":"Sat, 20 Jan 2024 11:55:01 GMT","inverseRate":0.0016585202565238},"kgs":{"code":"KGS","alphaCode":"KGS","numericCode":"417","name":"Kyrgyzstan Som","rate":87.971306671667,"date":"Sat, 20 Jan 2024 11:55:01 GMT","inverseRate":0.011367342805675}}